setup.cfg
setup.py
object_storage/__init__.py
object_storage/client.py
object_storage/consts.py
object_storage/container.py
object_storage/errors.py
object_storage/storage_object.py
object_storage/utils.py
object_storage/transport/__init__.py
object_storage/transport/httplib2conn.py
object_storage/transport/requestsconn.py
object_storage/transport/twist.py
softlayer_object_storage.egg-info/PKG-INFO
softlayer_object_storage.egg-info/SOURCES.txt
softlayer_object_storage.egg-info/dependency_links.txt
softlayer_object_storage.egg-info/requires.txt
softlayer_object_storage.egg-info/top_level.txt