Metadata-Version: 1.0
Name: softlayer-object-storage
Version: 0.4.7
Summary: Softlayer Object Storage client bindings for python.
Home-page: https://github.com/softlayer/softlayer-object-storage-python
Author: SoftLayer Technologies, Inc.
Author-email: sldn@softlayer.com
License: MIT
Platform: UNKNOWN
Classifier: Environment :: Console
Classifier: Intended Audience :: Developers
Classifier: License :: OSI Approved :: MIT License
Classifier: Programming Language :: Python
Classifier: Topic :: Internet :: WWW/HTTP
Classifier: Topic :: Software Development :: Libraries :: Python Modules
Classifier: Topic :: System :: Distributed Computing
Classifier: Topic :: Utilities
